{
    "canvas_width": 512,
    "canvas_height": 768,
    "people": [
        {
            "pose_keypoints_2d": [
                276, 187, 1,
                307, 293, 1,
                236, 292, 1,
                163, 434, 1,
                286, 420, 1,
                379, 293, 1,
                351, 440, 1,
                248, 424, 1,
                243, 551, 1,
                243, 764, 1,
                0, 0, 0,
                345, 574, 1,
                347, 768, 1,
                0, 0, 0,
                258, 170, 1,
                303, 159, 1,
                245, 181, 1,
                354, 162, 1
            ],
            "hand_left_keypoints_2d": [
                216, 406, 1,
                0, 0, 0,
                0, 0, 0,
                0, 0, 0,
                0, 0, 0,
                197, 383, 1,
                187, 377, 1,
                178, 377, 1,
                171, 380, 1,
                194, 388, 1,
                183, 382, 1,
                175, 383, 1,
                169, 386, 1,
                191, 394, 1,
                181, 390, 1,
                173, 390, 1,
                169, 393, 1,
                190, 399, 1,
                182, 399, 1,
                175, 400, 1,
                169, 404, 1
            ]
        }
    ]
}
